policyengine_uk_data/__init__.py
policyengine_uk_data/datasets/__init__.py
policyengine_uk_data/datasets/spi.py
policyengine_uk_data/datasets/frs/__init__.py
policyengine_uk_data/datasets/frs/dwp_frs.py
policyengine_uk_data/datasets/frs/enhanced_frs.py
policyengine_uk_data/datasets/frs/extended_frs.py
policyengine_uk_data/datasets/frs/frs.py
policyengine_uk_data/datasets/frs/local_areas/constituencies/calibrate.py
policyengine_uk_data/datasets/frs/local_areas/constituencies/loss.py
policyengine_uk_data/datasets/frs/local_areas/constituencies/transform_constituencies.py
policyengine_uk_data/datasets/frs/local_areas/constituencies/mapping_2010_to_2024/construct_mapping_matrix.py
policyengine_uk_data/datasets/frs/local_areas/constituencies/mapping_2010_to_2024/mapping_matrix.csv
policyengine_uk_data/datasets/frs/local_areas/constituencies/mapping_2010_to_2024/mapping_raw.csv
policyengine_uk_data/datasets/frs/local_areas/constituencies/mapping_2010_to_2024/total_income_2024.ipynb
policyengine_uk_data/datasets/frs/local_areas/constituencies/targets/README.md
policyengine_uk_data/datasets/frs/local_areas/constituencies/targets/__init__.py
policyengine_uk_data/datasets/frs/local_areas/constituencies/targets/age.csv
policyengine_uk_data/datasets/frs/local_areas/constituencies/targets/create_employment_incomes.py
policyengine_uk_data/datasets/frs/local_areas/constituencies/targets/employment_income.csv
policyengine_uk_data/datasets/frs/local_areas/constituencies/targets/fill_missing_age_demographics.py
policyengine_uk_data/datasets/frs/local_areas/constituencies/targets/nomis_earning_jobs_data.xlsx
policyengine_uk_data/datasets/frs/local_areas/constituencies/targets/total_income.csv
policyengine_uk_data/datasets/frs/local_areas/local_authorities/calibrate.py
policyengine_uk_data/datasets/frs/local_areas/local_authorities/loss.py
policyengine_uk_data/datasets/frs/local_areas/local_authorities/targets/README.md
policyengine_uk_data-1.11.1.dist-info/METADATA
policyengine_uk_data-1.11.1.dist-info/WHEEL
policyengine_uk_data-1.11.1.dist-info/top_level.txt
policyengine_uk_data-1.11.1.dist-info/RECORD
